LICENSE.txt
README.md
setup.cfg
setup.py
flask_arch/__init__.py
flask_arch/base.py
flask_arch/blocks.py
flask_arch/callbacks.py
flask_arch/exceptions.py
flask_arch/tags.py
flask_arch/utils.py
flask_arch.egg-info/PKG-INFO
flask_arch.egg-info/SOURCES.txt
flask_arch.egg-info/dependency_links.txt
flask_arch.egg-info/not-zip-safe
flask_arch.egg-info/requires.txt
flask_arch.egg-info/top_level.txt
flask_arch/auth/__init__.py
flask_arch/auth/base.py
flask_arch/auth/blocks.py
flask_arch/builtins/__init__.py
flask_arch/builtins/auth.py
flask_arch/builtins/cms.py
flask_arch/builtins/password.py
flask_arch/builtins/sql.py
flask_arch/builtins/user_manage.py
flask_arch/cms/__init__.py
flask_arch/cms/base.py
flask_arch/cms/blocks.py
flask_arch/cms/default.py
flask_arch/cms/files.py
flask_arch/cms/persist/__init__.py
flask_arch/cms/persist/sql/__init__.py
flask_arch/cms/volatile/__init__.py
flask_arch/cms/volatile/procmem/__init__.py
flask_arch/user/__init__.py
flask_arch/user/access_policies.py
flask_arch/user/base.py
flask_arch/user/persist/__init__.py
flask_arch/user/persist/sql/__init__.py
flask_arch/user/persist/sql/base.py
flask_arch/user/persist/sql/role.py
flask_arch/user/volatile/__init__.py
flask_arch/user/volatile/procmem/__init__.py
flask_arch/user/volatile/procmem/base.py